FibonacciMariam/__init__.py
FibonacciMariam/example.py
FibonacciMariam-0.0.1.dist-info/LICENSE.txt
FibonacciMariam-0.0.1.dist-info/METADATA
FibonacciMariam-0.0.1.dist-info/WHEEL
FibonacciMariam-0.0.1.dist-info/top_level.txt
FibonacciMariam-0.0.1.dist-info/RECORD
